topsis/__init__.py
topsis/__main__.py
Topsis_VardaanK_102003295-1.0.0.dist-info/LICENSE.txt
Topsis_VardaanK_102003295-1.0.0.dist-info/METADATA
Topsis_VardaanK_102003295-1.0.0.dist-info/WHEEL
Topsis_VardaanK_102003295-1.0.0.dist-info/entry_points.txt
Topsis_VardaanK_102003295-1.0.0.dist-info/top_level.txt
Topsis_VardaanK_102003295-1.0.0.dist-info/RECORD
