Metadata-Version: 2.1
Name: Topsis-VardaanK-102003295
Version: 1.0.0
Summary: A Python package implementing TOPSIS technique used to solve the multi criteria decision making problems.
Home-page: 
Author: Vardaan Khosla
Author-email: khoslavardaan1@gmail.com
License: MIT
Platform: UNKNOWN
Classifier: License :: OSI Approved :: MIT License
Classifier: Programming Language :: Python :: 3
Classifier: Programming Language :: Python :: 3.7
License-File: LICENSE.txt
Requires-Dist: numpy
Requires-Dist: pandas
